{
  "id": "0c614629-6618-4682-b70f-43a7cfaeca98",
  "record_type": "capture",
  "pattern_slug": "wyckoff-spring-reversal-v1",
  "symbol": "XRPUSDT",
  "user_id": "founder_seed",
  "outcome_id": null,
  "capture_id": "f36467a4-b20d-4b55-bd17-c5b2dcf2d089",
  "transition_id": null,
  "scan_id": null,
  "created_at": "2026-04-20T02:03:09.085203",
  "payload": {
    "capture_kind": "manual_hypothesis",
    "pattern_version": 1,
    "phase": "SPRING",
    "timeframe": "1h",
    "status": "pending_outcome",
    "user_note": "Test setup 4",
    "outcome_id": null,
    "verdict_id": null
  }
}