{
  "id": "9576e4d4-80ee-40e5-9357-84dcfcd341c7",
  "record_type": "outcome",
  "pattern_slug": "tradoor-oi-reversal-v1",
  "symbol": "PTBUSDT",
  "user_id": null,
  "outcome_id": "37da8145",
  "capture_id": null,
  "transition_id": null,
  "scan_id": null,
  "created_at": "2026-04-16T00:25:06.416151",
  "payload": {
    "previous_outcome": "pending",
    "outcome": "success",
    "breakout_at": null,
    "invalidated_at": null,
    "peak_price": 115.0,
    "exit_price": 110.0,
    "max_gain_pct": 0.15,
    "exit_return_pct": 0.1,
    "duration_hours": null
  }
}